{
  "OVER 1.5 STARTED HERE": [
    {
      "teams": "Spain Women vs Switzerland Women",
      "analysis": "All 6/6 H2H are over 1.5 Goals"
    },
    {
      "teams": "FC KTP vs FC Inter Turku",
      "analysis": "All 10/10 H2H are over 1.5 Goals"
    },
    {
      "teams": "Modbury Jets vs FK Beograd",
      "analysis": "All 10/10 H2H are over 1.5 Goals"
    },
    {
      "teams": "West Torrens Birkalla vs Adelaide United Youth",
      "analysis": "All 9/9 H2H are over 1.5 Goals"
    },
    {
      "teams": "Brunswick City vs Manningham United Blues",
      "analysis": "All 7/7 H2H are over 1.5 Goals"
    },
    {
      "teams": "SK Dynamo Ceske Budejovice vs FC Zbrojovka Brno",
      "analysis": "All 10/10 H2H are over 1.5 Goals"
    },
    {
      "teams": "FCI Levadia U21 vs Talinna Kalev U21",
      "analysis": "All 10/10 H2H are over 1.5 Goals"
    },
    {
      "teams": "Leiknir Reykjavik vs Throttur Reykjavik",
      "analysis": "All 10/10 H2H are over 1.5 Goals"
    },
    {
      "teams": "Shamrock Rovers vs Wexford FC",
      "analysis": "All 6/6 H2H are over 1.5 Goals"
    },
    {
      "teams": "FC Astana vs FC Turan",
      "analysis": "All 7/7 H2H are over 1.5 Goals"
    },
    {
      "teams": "Alianza Atletico vs Sport Huancayo",
      "analysis": "All 5/5 H2H are over 1.5 Goals"
    },
    {
      "teams": "Radomlje vs Aluminij",
      "analysis": "All 10/10 H2H are over 1.5 Goals"
    }
  ],
  "OVER 2.5 STARTED HERE": [
    {
      "teams": "Garuda FC vs University Azzurri FC",
      "analysis": "All 5/5 H2H are over 2.5 Goals"
    },
    {
      "teams": "Uruguay W vs Peru W",
      "analysis": "All 3/3 H2H are over 2.5 Goals"
    }
  ],
  "OVER 3.5 STARTED HERE": [],
  "WIN STARTED HERE": [
    {
      "teams": "Erzgebirge Aue vs Borussia M'gladbach",
      "winner": "Borussia M'gladbach",
      "analysis": "Borussia M'gladbach won all 4/4 H2H matches"
    },
    {
      "teams": "Uruguay W vs Peru W",
      "winner": "Uruguay W",
      "analysis": "Uruguay W won all 3/3 H2H matches"
    }
  ]
}